<clients>
  <client id="0">
    <planche id="0" nombre="10" date="14.06.20" prix="300.00">
      <dim L="50.00" l="40.00" />
    </planche>
    <planche id="1" nombre="5" date="04.05.23" prix="-200.00">
      <dim L="50.00" l="100.00" />
    </planche>
    <planche id="2" nombre="3" date="16.05.22" prix="950.00">
      <dim L="40.00" l="60.00" />
    </planche>
  </client>
  <client id="1">
    <planche id="0" nombre="10" date="14.06.12" prix="300.00">
      <dim L="50.00" l="40.00" />
    </planche>
    <planche id="2" nombre="10" date="14.06.24" prix="300">
      <dim L="50.00" l="40.00" />
    </planche>
  </client>
</clients>
